{"nodes": [{"id": "packages_testing_src_nest_test_utils_ts", "label": "nest-test-utils.ts", "file_type": "code", "source_file": "packages/testing/src/nest-test-utils.ts", "source_location": "L1"}, {"id": "nest_test_utils_createtestapp", "label": "createTestApp()", "file_type": "code", "source_file": "packages/testing/src/nest-test-utils.ts", "source_location": "L4"}, {"id": "nest_test_utils_mockjwtpayload", "label": "mockJwtPayload()", "file_type": "code", "source_file": "packages/testing/src/nest-test-utils.ts", "source_location": "L21"}], "edges": [{"source": "packages_testing_src_nest_test_utils_ts", "target": "common", "relation": "imports_from", "confidence": "EXTRACTED", "source_file": "packages/testing/src/nest-test-utils.ts", "source_location": "L1", "weight": 1.0}, {"source": "packages_testing_src_nest_test_utils_ts", "target": "testing", "relation": "imports_from", "confidence": "EXTRACTED", "source_file": "packages/testing/src/nest-test-utils.ts", "source_location": "L2", "weight": 1.0}, {"source": "packages_testing_src_nest_test_utils_ts", "target": "nest_test_utils_createtestapp", "relation": "contains", "confidence": "EXTRACTED", "source_file": "packages/testing/src/nest-test-utils.ts", "source_location": "L4", "weight": 1.0}, {"source": "packages_testing_src_nest_test_utils_ts", "target": "nest_test_utils_mockjwtpayload", "relation": "contains", "confidence": "EXTRACTED", "source_file": "packages/testing/src/nest-test-utils.ts", "source_location": "L21", "weight": 1.0}], "raw_calls": [{"caller_nid": "nest_test_utils_createtestapp", "callee": "compile", "source_file": "packages/testing/src/nest-test-utils.ts", "source_location": "L5"}, {"caller_nid": "nest_test_utils_createtestapp", "callee": "createTestingModule", "source_file": "packages/testing/src/nest-test-utils.ts", "source_location": "L5"}, {"caller_nid": "nest_test_utils_createtestapp", "callee": "createNestApplication", "source_file": "packages/testing/src/nest-test-utils.ts", "source_location": "L6"}, {"caller_nid": "nest_test_utils_createtestapp", "callee": "useGlobalPipes", "source_file": "packages/testing/src/nest-test-utils.ts", "source_location": "L8"}, {"caller_nid": "nest_test_utils_createtestapp", "callee": "init", "source_file": "packages/testing/src/nest-test-utils.ts", "source_location": "L17"}]}