{"nodes": [{"id": "packages_testing_src_db_setup_ts", "label": "db-setup.ts", "file_type": "code", "source_file": "packages/testing/src/db-setup.ts", "source_location": "L1"}, {"id": "db_setup_gettestprisma", "label": "getTestPrisma()", "file_type": "code", "source_file": "packages/testing/src/db-setup.ts", "source_location": "L5"}, {"id": "db_setup_cleanuptestdb", "label": "cleanupTestDb()", "file_type": "code", "source_file": "packages/testing/src/db-setup.ts", "source_location": "L14"}, {"id": "db_setup_disconnecttestdb", "label": "disconnectTestDb()", "file_type": "code", "source_file": "packages/testing/src/db-setup.ts", "source_location": "L26"}], "edges": [{"source": "packages_testing_src_db_setup_ts", "target": "client", "relation": "imports_from", "confidence": "EXTRACTED", "source_file": "packages/testing/src/db-setup.ts", "source_location": "L1", "weight": 1.0}, {"source": "packages_testing_src_db_setup_ts", "target": "db_setup_gettestprisma", "relation": "contains", "confidence": "EXTRACTED", "source_file": "packages/testing/src/db-setup.ts", "source_location": "L5", "weight": 1.0}, {"source": "packages_testing_src_db_setup_ts", "target": "db_setup_cleanuptestdb", "relation": "contains", "confidence": "EXTRACTED", "source_file": "packages/testing/src/db-setup.ts", "source_location": "L14", "weight": 1.0}, {"source": "packages_testing_src_db_setup_ts", "target": "db_setup_disconnecttestdb", "relation": "contains", "confidence": "EXTRACTED", "source_file": "packages/testing/src/db-setup.ts", "source_location": "L26", "weight": 1.0}], "raw_calls": [{"caller_nid": "db_setup_cleanuptestdb", "callee": "$executeRawUnsafe", "source_file": "packages/testing/src/db-setup.ts", "source_location": "L22"}, {"caller_nid": "db_setup_disconnecttestdb", "callee": "$disconnect", "source_file": "packages/testing/src/db-setup.ts", "source_location": "L27"}]}