{"nodes": [{"id": "packages_utils_src_string_ts", "label": "string.ts", "file_type": "code", "source_file": "packages/utils/src/string.ts", "source_location": "L1"}, {"id": "string_slugify", "label": "slugify()", "file_type": "code", "source_file": "packages/utils/src/string.ts", "source_location": "L1"}, {"id": "string_capitalizefirst", "label": "capitalizeFirst()", "file_type": "code", "source_file": "packages/utils/src/string.ts", "source_location": "L10"}, {"id": "string_titlecase", "label": "titleCase()", "file_type": "code", "source_file": "packages/utils/src/string.ts", "source_location": "L15"}, {"id": "string_truncate", "label": "truncate()", "file_type": "code", "source_file": "packages/utils/src/string.ts", "source_location": "L19"}, {"id": "string_maskemail", "label": "maskEmail()", "file_type": "code", "source_file": "packages/utils/src/string.ts", "source_location": "L24"}, {"id": "string_maskphone", "label": "maskPhone()", "file_type": "code", "source_file": "packages/utils/src/string.ts", "source_location": "L31"}, {"id": "string_generateadmissionnumber", "label": "generateAdmissionNumber()", "file_type": "code", "source_file": "packages/utils/src/string.ts", "source_location": "L35"}, {"id": "string_generatereceiptnumber", "label": "generateReceiptNumber()", "file_type": "code", "source_file": "packages/utils/src/string.ts", "source_location": "L43"}], "edges": [{"source": "packages_utils_src_string_ts", "target": "string_slugify", "relation": "contains", "confidence": "EXTRACTED", "source_file": "packages/utils/src/string.ts", "source_location": "L1", "weight": 1.0}, {"source": "packages_utils_src_string_ts", "target": "string_capitalizefirst", "relation": "contains", "confidence": "EXTRACTED", "source_file": "packages/utils/src/string.ts", "source_location": "L10", "weight": 1.0}, {"source": "packages_utils_src_string_ts", "target": "string_titlecase", "relation": "contains", "confidence": "EXTRACTED", "source_file": "packages/utils/src/string.ts", "source_location": "L15", "weight": 1.0}, {"source": "packages_utils_src_string_ts", "target": "string_truncate", "relation": "contains", "confidence": "EXTRACTED", "source_file": "packages/utils/src/string.ts", "source_location": "L19", "weight": 1.0}, {"source": "packages_utils_src_string_ts", "target": "string_maskemail", "relation": "contains", "confidence": "EXTRACTED", "source_file": "packages/utils/src/string.ts", "source_location": "L24", "weight": 1.0}, {"source": "packages_utils_src_string_ts", "target": "string_maskphone", "relation": "contains", "confidence": "EXTRACTED", "source_file": "packages/utils/src/string.ts", "source_location": "L31", "weight": 1.0}, {"source": "packages_utils_src_string_ts", "target": "string_generateadmissionnumber", "relation": "contains", "confidence": "EXTRACTED", "source_file": "packages/utils/src/string.ts", "source_location": "L35", "weight": 1.0}, {"source": "packages_utils_src_string_ts", "target": "string_generatereceiptnumber", "relation": "contains", "confidence": "EXTRACTED", "source_file": "packages/utils/src/string.ts", "source_location": "L43", "weight": 1.0}], "raw_calls": [{"caller_nid": "string_slugify", "callee": "replace", "source_file": "packages/utils/src/string.ts", "source_location": "L2"}, {"caller_nid": "string_slugify", "callee": "replace", "source_file": "packages/utils/src/string.ts", "source_location": "L2"}, {"caller_nid": "string_slugify", "callee": "replace", "source_file": "packages/utils/src/string.ts", "source_location": "L2"}, {"caller_nid": "string_slugify", "callee": "trim", "source_file": "packages/utils/src/string.ts", "source_location": "L2"}, {"caller_nid": "string_slugify", "callee": "toLowerCase", "source_file": "packages/utils/src/string.ts", "source_location": "L2"}, {"caller_nid": "string_capitalizefirst", "callee": "toUpperCase", "source_file": "packages/utils/src/string.ts", "source_location": "L12"}, {"caller_nid": "string_capitalizefirst", "callee": "charAt", "source_file": "packages/utils/src/string.ts", "source_location": "L12"}, {"caller_nid": "string_capitalizefirst", "callee": "toLowerCase", "source_file": "packages/utils/src/string.ts", "source_location": "L12"}, {"caller_nid": "string_capitalizefirst", "callee": "slice", "source_file": "packages/utils/src/string.ts", "source_location": "L12"}, {"caller_nid": "string_titlecase", "callee": "replace", "source_file": "packages/utils/src/string.ts", "source_location": "L16"}, {"caller_nid": "string_truncate", "callee": "slice", "source_file": "packages/utils/src/string.ts", "source_location": "L21"}, {"caller_nid": "string_maskemail", "callee": "split", "source_file": "packages/utils/src/string.ts", "source_location": "L25"}, {"caller_nid": "string_maskemail", "callee": "slice", "source_file": "packages/utils/src/string.ts", "source_location": "L27"}, {"caller_nid": "string_maskemail", "callee": "repeat", "source_file": "packages/utils/src/string.ts", "source_location": "L28"}, {"caller_nid": "string_maskemail", "callee": "max", "source_file": "packages/utils/src/string.ts", "source_location": "L28"}, {"caller_nid": "string_maskphone", "callee": "replace", "source_file": "packages/utils/src/string.ts", "source_location": "L32"}, {"caller_nid": "string_generateadmissionnumber", "callee": "padStart", "source_file": "packages/utils/src/string.ts", "source_location": "L40"}, {"caller_nid": "string_generateadmissionnumber", "callee": "String", "source_file": "packages/utils/src/string.ts", "source_location": "L40"}, {"caller_nid": "string_generatereceiptnumber", "callee": "padStart", "source_file": "packages/utils/src/string.ts", "source_location": "L44"}, {"caller_nid": "string_generatereceiptnumber", "callee": "String", "source_file": "packages/utils/src/string.ts", "source_location": "L44"}]}